requirements.txt
setup.py
django_celery_task_queue/__init__.py
django_celery_task_queue/classes.py
django_celery_task_queue/utils.py
django_celery_task_queue.egg-info/PKG-INFO
django_celery_task_queue.egg-info/SOURCES.txt
django_celery_task_queue.egg-info/dependency_links.txt
django_celery_task_queue.egg-info/requires.txt
django_celery_task_queue.egg-info/top_level.txt
django_celery_task_queue/migrations/0001_initial.py
django_celery_task_queue/migrations/__init__.py
django_celery_task_queue/models/__init__.py
django_celery_task_queue/models/abstract_task.py
django_celery_task_queue/models/task_queue_exc.py