Metadata-Version: 2.1
Name: django-celery-task-queue
Version: 2020.7.2
Summary: Django Celery task queue models, classes and utils
Home-page: https://github.com/andrewp-as-is/django-celery-task-queue.py
License: Unlicense
Keywords: django celery task queue
Platform: UNKNOWN
Classifier: Framework :: Django
Classifier: License :: Public Domain
Classifier: Operating System :: OS Independent
Classifier: Programming Language :: Python :: 3
